tag_validate/__init__.py
tag_validate/_version.py
tag_validate/cli.py
tag_validate/github_keys.py
tag_validate/models.py
tag_validate/signature.py
tag_validate/tag_operations.py
tag_validate/validation.py
tag_validate/workflow.py
tag_validate-0.2.0.dist-info/METADATA
tag_validate-0.2.0.dist-info/WHEEL
tag_validate-0.2.0.dist-info/entry_points.txt
tag_validate-0.2.0.dist-info/licenses/LICENSE
tag_validate-0.2.0.dist-info/RECORD
