Metadata-Version: 2.4
Name: tag-validate
Version: 0.2.0
Summary: GitHub tag validation tool with cryptographic signature verification and GitHub key registry checks
Project-URL: Homepage, https://github.com/lfreleng-actions/tag-validate-action
Project-URL: Repository, https://github.com/lfreleng-actions/tag-validate-action
Project-URL: Bug Tracker, https://github.com/lfreleng-actions/tag-validate-action/issues
Project-URL: Documentation, https://github.com/lfreleng-actions/tag-validate-action/blob/main/README.md
Author-email: Matthew Watkins <93649628+ModeSevenIndustrialSolutions@users.noreply.github.com>
License-Expression: Apache-2.0
License-File: LICENSE
Classifier: Intended Audience :: Developers
Classifier: Operating System :: MacOS
Classifier: Operating System :: Microsoft :: Windows
Classifier: Operating System :: Unix
Classifier: Programming Language :: Python
Classifier: Programming Language :: Python :: 3
Classifier: Programming Language :: Python :: 3 :: Only
Classifier: Programming Language :: Python :: 3.10
Classifier: Programming Language :: Python :: 3.11
Classifier: Programming Language :: Python :: 3.12
Classifier: Programming Language :: Python :: 3.13
Classifier: Topic :: Software Development
Classifier: Topic :: Software Development :: Version Control :: Git
Requires-Python: >=3.10
Requires-Dist: aiolimiter>=1.2.1
Requires-Dist: cryptography>=46.0.3
Requires-Dist: dependamerge>=0.1.19
Requires-Dist: httpx[http2]>=0.28.1
Requires-Dist: packaging>=24.2
Requires-Dist: pydantic>=2.12.5
Requires-Dist: python-gnupg>=0.5.3
Requires-Dist: rich>=14.2.0
Requires-Dist: typer>=0.21.1
Provides-Extra: dev
Requires-Dist: black>=25.12.0; extra == 'dev'
Requires-Dist: coverage[toml]>=7.13.1; extra == 'dev'
Requires-Dist: mypy>=1.19.1; extra == 'dev'
Requires-Dist: pytest-asyncio>=1.3.0; extra == 'dev'
Requires-Dist: pytest-cov>=7.0.0; extra == 'dev'
Requires-Dist: pytest-mock>=3.15.1; extra == 'dev'
Requires-Dist: pytest>=9.0.2; extra == 'dev'
Requires-Dist: responses>=0.25.8; extra == 'dev'
Requires-Dist: ruff>=0.14.11; extra == 'dev'
Requires-Dist: types-requests>=2.32.4.20250809; extra == 'dev'
